{
  "schema": "lit-iso.spriteforge.action.v1",
  "action": "walk",
  "frames": 6,
  "fps": 10,
  "loop": true,
  "loop_start": 1,
  "loop_end": 5,
  "loop_range": [
    1,
    5
  ],
  "loop_note": "Playback should loop loop_range; frame 0 remains available as the generation/idle anchor.",
  "anchor_frame": 0,
  "anchor_note": "frame 0 is byte-identical to the shared idle anchor pose for each direction.",
  "weapon_hand": "none",
  "engine_default": "frames",
  "engine_by_target_size": {
    ">=96": "video"
  },
  "directions": [
    "S",
    "SE",
    "E",
    "NE",
    "N",
    "NW",
    "W",
    "SW"
  ],
  "frame_size": [
    512,
    512
  ],
  "background": "transparent",
  "pose_library_version": "0.2.1-p2-walk-readability",
  "source": {
    "method": "deterministic_body18_openpose_skeletons",
    "derived_from": "Tools/AssetForge/build_litiso_openpose_direction_library.py geometry conventions",
    "license": "project-internal skeleton controls; no oracle art pixels included"
  },
  "mirrorable": {
    "W": "E",
    "NW": "NE",
    "SW": "SE"
  },
  "mirror_note": "W-side directions may be generated by mirroring E-side results only for symmetric character designs.",
  "frames_meta": [
    {
      "direction": "S",
      "direction_word": "south",
      "frame_index": 0,
      "phase": "anchor",
      "pose_png": "walk/S/frame_000.png",
      "openpose_json": "walk/S/frame_000.openpose.json",
      "sha256": "da8701100168566dba88cb2318ce09c18a301774e7771cd983932e88ea9ab4d3",
      "shared_idle_anchor": true
    },
    {
      "direction": "S",
      "direction_word": "south",
      "frame_index": 1,
      "phase": "near_forward",
      "pose_png": "walk/S/frame_001.png",
      "openpose_json": "walk/S/frame_001.openpose.json",
      "sha256": "2a19161fa617dad1b111ace09378889674178b8c5fd1f20955506e10000fdf32",
      "shared_idle_anchor": false
    },
    {
      "direction": "S",
      "direction_word": "south",
      "frame_index": 2,
      "phase": "near_contact",
      "pose_png": "walk/S/frame_002.png",
      "openpose_json": "walk/S/frame_002.openpose.json",
      "sha256": "a9119d326a46e9adbca72570bc7fbb337cb9ea8273de5a5c4aa99a2e271763e5",
      "shared_idle_anchor": false
    },
    {
      "direction": "S",
      "direction_word": "south",
      "frame_index": 3,
      "phase": "far_forward",
      "pose_png": "walk/S/frame_003.png",
      "openpose_json": "walk/S/frame_003.openpose.json",
      "sha256": "31ae6b06f7fa105ffe33f494a1106ee3aa0ffb2b56b790bcc822735efe51709d",
      "shared_idle_anchor": false
    },
    {
      "direction": "S",
      "direction_word": "south",
      "frame_index": 4,
      "phase": "far_contact",
      "pose_png": "walk/S/frame_004.png",
      "openpose_json": "walk/S/frame_004.openpose.json",
      "sha256": "6644a398f69efd29c235c7bc6ecdc47b4519e0bb0f8885ee20d9106b9cf05f1b",
      "shared_idle_anchor": false
    },
    {
      "direction": "S",
      "direction_word": "south",
      "frame_index": 5,
      "phase": "recover",
      "pose_png": "walk/S/frame_005.png",
      "openpose_json": "walk/S/frame_005.openpose.json",
      "sha256": "c2201e0c2031081bc6610aef4ac5f778d0e6dbb5d6a32d6ebe9f474ea2f9bbf9",
      "shared_idle_anchor": false
    },
    {
      "direction": "SE",
      "direction_word": "south-east",
      "frame_index": 0,
      "phase": "anchor",
      "pose_png": "walk/SE/frame_000.png",
      "openpose_json": "walk/SE/frame_000.openpose.json",
      "sha256": "3c5417c0dca39b7cf1deba0c62accef8b311f44e67fbfdc1e72cdb545486f144",
      "shared_idle_anchor": true
    },
    {
      "direction": "SE",
      "direction_word": "south-east",
      "frame_index": 1,
      "phase": "near_forward",
      "pose_png": "walk/SE/frame_001.png",
      "openpose_json": "walk/SE/frame_001.openpose.json",
      "sha256": "546044e92a6e575c8ca1d0d57292e38d5013981eb20b703e06fb85150fd36d0a",
      "shared_idle_anchor": false
    },
    {
      "direction": "SE",
      "direction_word": "south-east",
      "frame_index": 2,
      "phase": "near_contact",
      "pose_png": "walk/SE/frame_002.png",
      "openpose_json": "walk/SE/frame_002.openpose.json",
      "sha256": "91addbf423d1c27b776eddc50d04446c88c7f99954558f486d3afb373c70f8d6",
      "shared_idle_anchor": false
    },
    {
      "direction": "SE",
      "direction_word": "south-east",
      "frame_index": 3,
      "phase": "far_forward",
      "pose_png": "walk/SE/frame_003.png",
      "openpose_json": "walk/SE/frame_003.openpose.json",
      "sha256": "b90f29bdd53b747fa76dbf8186925cb9dcb0a7b9015cc74ffb94aefa42be5d46",
      "shared_idle_anchor": false
    },
    {
      "direction": "SE",
      "direction_word": "south-east",
      "frame_index": 4,
      "phase": "far_contact",
      "pose_png": "walk/SE/frame_004.png",
      "openpose_json": "walk/SE/frame_004.openpose.json",
      "sha256": "65236f504b8545335459f0c839bfcd070af59a5f562bba0c4885bf18745c70d5",
      "shared_idle_anchor": false
    },
    {
      "direction": "SE",
      "direction_word": "south-east",
      "frame_index": 5,
      "phase": "recover",
      "pose_png": "walk/SE/frame_005.png",
      "openpose_json": "walk/SE/frame_005.openpose.json",
      "sha256": "b79e2fd9a90cb4d71d2f809abf8d3e4585ef4888daecc56a347748b65c53c008",
      "shared_idle_anchor": false
    },
    {
      "direction": "E",
      "direction_word": "east",
      "frame_index": 0,
      "phase": "anchor",
      "pose_png": "walk/E/frame_000.png",
      "openpose_json": "walk/E/frame_000.openpose.json",
      "sha256": "ad2ba817667dac97d53f000ca376c4e92e5fd46e810645098ff3396fe2d68f04",
      "shared_idle_anchor": true
    },
    {
      "direction": "E",
      "direction_word": "east",
      "frame_index": 1,
      "phase": "near_forward",
      "pose_png": "walk/E/frame_001.png",
      "openpose_json": "walk/E/frame_001.openpose.json",
      "sha256": "86a6074b54d76da0e49638276e155d84c2a5d17e2b97e63c98b7398a07e4b688",
      "shared_idle_anchor": false
    },
    {
      "direction": "E",
      "direction_word": "east",
      "frame_index": 2,
      "phase": "near_contact",
      "pose_png": "walk/E/frame_002.png",
      "openpose_json": "walk/E/frame_002.openpose.json",
      "sha256": "a7754cc8cbba28625c7d402df755fe6941c7ba678df85c6cb94e130e15059dc6",
      "shared_idle_anchor": false
    },
    {
      "direction": "E",
      "direction_word": "east",
      "frame_index": 3,
      "phase": "far_forward",
      "pose_png": "walk/E/frame_003.png",
      "openpose_json": "walk/E/frame_003.openpose.json",
      "sha256": "504e904c9123053da687f1613fcc62446d888a03ab8c3d5c50b5d72ea6069e4b",
      "shared_idle_anchor": false
    },
    {
      "direction": "E",
      "direction_word": "east",
      "frame_index": 4,
      "phase": "far_contact",
      "pose_png": "walk/E/frame_004.png",
      "openpose_json": "walk/E/frame_004.openpose.json",
      "sha256": "2e17dc350049194692ac8a642754f6133d91a71c39e8034c5ab858ad3db37bb5",
      "shared_idle_anchor": false
    },
    {
      "direction": "E",
      "direction_word": "east",
      "frame_index": 5,
      "phase": "recover",
      "pose_png": "walk/E/frame_005.png",
      "openpose_json": "walk/E/frame_005.openpose.json",
      "sha256": "430912a35571616254e501dc2606764705357c445abf335a9dc41fb3ed5ecb1c",
      "shared_idle_anchor": false
    },
    {
      "direction": "NE",
      "direction_word": "north-east",
      "frame_index": 0,
      "phase": "anchor",
      "pose_png": "walk/NE/frame_000.png",
      "openpose_json": "walk/NE/frame_000.openpose.json",
      "sha256": "da6a9da382c22ae5d40d2d04e38b8aedef5568d36b2def8dd35f4e3ddf1b6214",
      "shared_idle_anchor": true
    },
    {
      "direction": "NE",
      "direction_word": "north-east",
      "frame_index": 1,
      "phase": "near_forward",
      "pose_png": "walk/NE/frame_001.png",
      "openpose_json": "walk/NE/frame_001.openpose.json",
      "sha256": "c4a308cb3cf80bc5794fbee08fe1f521bc6dda0e017f9fe6dc1b008e532df3c6",
      "shared_idle_anchor": false
    },
    {
      "direction": "NE",
      "direction_word": "north-east",
      "frame_index": 2,
      "phase": "near_contact",
      "pose_png": "walk/NE/frame_002.png",
      "openpose_json": "walk/NE/frame_002.openpose.json",
      "sha256": "8e2a8a69345172c8eaf85631d97facc113b8290a9676fcc662efdb9e6dc4dc68",
      "shared_idle_anchor": false
    },
    {
      "direction": "NE",
      "direction_word": "north-east",
      "frame_index": 3,
      "phase": "far_forward",
      "pose_png": "walk/NE/frame_003.png",
      "openpose_json": "walk/NE/frame_003.openpose.json",
      "sha256": "16bc205fe10ebf924dec48b946961d66b5e83db2a26dbb4dc2f7a56dee2aa7f4",
      "shared_idle_anchor": false
    },
    {
      "direction": "NE",
      "direction_word": "north-east",
      "frame_index": 4,
      "phase": "far_contact",
      "pose_png": "walk/NE/frame_004.png",
      "openpose_json": "walk/NE/frame_004.openpose.json",
      "sha256": "5f9e7c76fefd6b9c3e2a6e15177caaa0a6ff0b406497f7274cd3e1b355bb1949",
      "shared_idle_anchor": false
    },
    {
      "direction": "NE",
      "direction_word": "north-east",
      "frame_index": 5,
      "phase": "recover",
      "pose_png": "walk/NE/frame_005.png",
      "openpose_json": "walk/NE/frame_005.openpose.json",
      "sha256": "f5467389ed458d3f897f0190cecd4a7c492ca5588fe16dccc229c4701347b09d",
      "shared_idle_anchor": false
    },
    {
      "direction": "N",
      "direction_word": "north",
      "frame_index": 0,
      "phase": "anchor",
      "pose_png": "walk/N/frame_000.png",
      "openpose_json": "walk/N/frame_000.openpose.json",
      "sha256": "8a329757c3aabc1d2502e3b78f5de3deb21a837cd94b7c32c48e4e34fe6f9668",
      "shared_idle_anchor": true
    },
    {
      "direction": "N",
      "direction_word": "north",
      "frame_index": 1,
      "phase": "near_forward",
      "pose_png": "walk/N/frame_001.png",
      "openpose_json": "walk/N/frame_001.openpose.json",
      "sha256": "01828f86921c0fbcee1ee7c822ba664134510821b0637baaccea99a23a4dc8c1",
      "shared_idle_anchor": false
    },
    {
      "direction": "N",
      "direction_word": "north",
      "frame_index": 2,
      "phase": "near_contact",
      "pose_png": "walk/N/frame_002.png",
      "openpose_json": "walk/N/frame_002.openpose.json",
      "sha256": "bd319780d22a6380b0d05d2216d2156d86db579bef175ff9dd382f39d7687ccc",
      "shared_idle_anchor": false
    },
    {
      "direction": "N",
      "direction_word": "north",
      "frame_index": 3,
      "phase": "far_forward",
      "pose_png": "walk/N/frame_003.png",
      "openpose_json": "walk/N/frame_003.openpose.json",
      "sha256": "aca24a65d1878ea9c61d40a308cfdf7a83917b09fe0c588acf48216c0bb56f8d",
      "shared_idle_anchor": false
    },
    {
      "direction": "N",
      "direction_word": "north",
      "frame_index": 4,
      "phase": "far_contact",
      "pose_png": "walk/N/frame_004.png",
      "openpose_json": "walk/N/frame_004.openpose.json",
      "sha256": "5b6a0778f3e8a1ba7ecd00b2947f5a1ebf9660dd717872ed8ccd35ee14c8cffe",
      "shared_idle_anchor": false
    },
    {
      "direction": "N",
      "direction_word": "north",
      "frame_index": 5,
      "phase": "recover",
      "pose_png": "walk/N/frame_005.png",
      "openpose_json": "walk/N/frame_005.openpose.json",
      "sha256": "2c537f4ed3dd8f2c902368c32ff7b5ce12da02f70418903dad2445b516847287",
      "shared_idle_anchor": false
    },
    {
      "direction": "NW",
      "direction_word": "north-west",
      "frame_index": 0,
      "phase": "anchor",
      "pose_png": "walk/NW/frame_000.png",
      "openpose_json": "walk/NW/frame_000.openpose.json",
      "sha256": "989f3d5cf525b0db462167906d3093336bf3007bbdc8289fd7ce45420f4c9380",
      "shared_idle_anchor": true
    },
    {
      "direction": "NW",
      "direction_word": "north-west",
      "frame_index": 1,
      "phase": "near_forward",
      "pose_png": "walk/NW/frame_001.png",
      "openpose_json": "walk/NW/frame_001.openpose.json",
      "sha256": "164ae3fc943aade511bdccd9f13b02a2cc2c3777cd9ffe20fc41a2677bbdd560",
      "shared_idle_anchor": false
    },
    {
      "direction": "NW",
      "direction_word": "north-west",
      "frame_index": 2,
      "phase": "near_contact",
      "pose_png": "walk/NW/frame_002.png",
      "openpose_json": "walk/NW/frame_002.openpose.json",
      "sha256": "e9f1225daa481d6e7b20ded3ecb789fd8708eb9fbb220a09ec2be84f74a146a2",
      "shared_idle_anchor": false
    },
    {
      "direction": "NW",
      "direction_word": "north-west",
      "frame_index": 3,
      "phase": "far_forward",
      "pose_png": "walk/NW/frame_003.png",
      "openpose_json": "walk/NW/frame_003.openpose.json",
      "sha256": "c6bd197d0a7aad785d06e90a47a8822e9f04a01155f15e8f1896853fd9a06fdb",
      "shared_idle_anchor": false
    },
    {
      "direction": "NW",
      "direction_word": "north-west",
      "frame_index": 4,
      "phase": "far_contact",
      "pose_png": "walk/NW/frame_004.png",
      "openpose_json": "walk/NW/frame_004.openpose.json",
      "sha256": "ecb9f19aa33abe8fd431908128781d04dfa7248886d9ea3e2a1a9e7b17dee99c",
      "shared_idle_anchor": false
    },
    {
      "direction": "NW",
      "direction_word": "north-west",
      "frame_index": 5,
      "phase": "recover",
      "pose_png": "walk/NW/frame_005.png",
      "openpose_json": "walk/NW/frame_005.openpose.json",
      "sha256": "8141c286c6ff3cb853b7d6ef7e5980d191659e4b78efa2370eb7a321abf1d219",
      "shared_idle_anchor": false
    },
    {
      "direction": "W",
      "direction_word": "west",
      "frame_index": 0,
      "phase": "anchor",
      "pose_png": "walk/W/frame_000.png",
      "openpose_json": "walk/W/frame_000.openpose.json",
      "sha256": "df7361c916921801f40e75ff63bbd38e17de684751173822adfe61fd05ec55f2",
      "shared_idle_anchor": true
    },
    {
      "direction": "W",
      "direction_word": "west",
      "frame_index": 1,
      "phase": "near_forward",
      "pose_png": "walk/W/frame_001.png",
      "openpose_json": "walk/W/frame_001.openpose.json",
      "sha256": "89232a2ff114f4417505b7b3e9a52810fe90897c6bd2684ce63b784b891576fa",
      "shared_idle_anchor": false
    },
    {
      "direction": "W",
      "direction_word": "west",
      "frame_index": 2,
      "phase": "near_contact",
      "pose_png": "walk/W/frame_002.png",
      "openpose_json": "walk/W/frame_002.openpose.json",
      "sha256": "4fbdff1ea7ee6e0066198787d9349957d4001e00abf832346d593574dd9f1f7d",
      "shared_idle_anchor": false
    },
    {
      "direction": "W",
      "direction_word": "west",
      "frame_index": 3,
      "phase": "far_forward",
      "pose_png": "walk/W/frame_003.png",
      "openpose_json": "walk/W/frame_003.openpose.json",
      "sha256": "360fac4a176b97a8f01a06e3e15d2c3d864bbd7e700aca318aa0b0689f118ed6",
      "shared_idle_anchor": false
    },
    {
      "direction": "W",
      "direction_word": "west",
      "frame_index": 4,
      "phase": "far_contact",
      "pose_png": "walk/W/frame_004.png",
      "openpose_json": "walk/W/frame_004.openpose.json",
      "sha256": "269468d70157098ca5d972e9dffbacf86c4bb6b92d6dc52a984d6fd4e5b7acea",
      "shared_idle_anchor": false
    },
    {
      "direction": "W",
      "direction_word": "west",
      "frame_index": 5,
      "phase": "recover",
      "pose_png": "walk/W/frame_005.png",
      "openpose_json": "walk/W/frame_005.openpose.json",
      "sha256": "913c8feb9af473e77338756e314ff62b27b5475e1c1f8650150026e9111eec64",
      "shared_idle_anchor": false
    },
    {
      "direction": "SW",
      "direction_word": "south-west",
      "frame_index": 0,
      "phase": "anchor",
      "pose_png": "walk/SW/frame_000.png",
      "openpose_json": "walk/SW/frame_000.openpose.json",
      "sha256": "db3b43d8fec3830ab06094b5969e21a58bd83292e887dfff2d2eadd2f5f71bd6",
      "shared_idle_anchor": true
    },
    {
      "direction": "SW",
      "direction_word": "south-west",
      "frame_index": 1,
      "phase": "near_forward",
      "pose_png": "walk/SW/frame_001.png",
      "openpose_json": "walk/SW/frame_001.openpose.json",
      "sha256": "0c3be3f91150b7a7941084b3bf22135c91f524074fcaf21ef678bfc3dde25b91",
      "shared_idle_anchor": false
    },
    {
      "direction": "SW",
      "direction_word": "south-west",
      "frame_index": 2,
      "phase": "near_contact",
      "pose_png": "walk/SW/frame_002.png",
      "openpose_json": "walk/SW/frame_002.openpose.json",
      "sha256": "e0ba508d8941c1ea84bb8a1c28b9caa8558d4dd1e3da1f1e2bf430616d30ecb1",
      "shared_idle_anchor": false
    },
    {
      "direction": "SW",
      "direction_word": "south-west",
      "frame_index": 3,
      "phase": "far_forward",
      "pose_png": "walk/SW/frame_003.png",
      "openpose_json": "walk/SW/frame_003.openpose.json",
      "sha256": "3398da9672109e729c3f5aecb7d3376345f7c41c730d85d7d292c38dd4aa3efc",
      "shared_idle_anchor": false
    },
    {
      "direction": "SW",
      "direction_word": "south-west",
      "frame_index": 4,
      "phase": "far_contact",
      "pose_png": "walk/SW/frame_004.png",
      "openpose_json": "walk/SW/frame_004.openpose.json",
      "sha256": "563c0abd2dc32907ccd41842ed4029492e9e9bbd7a29cc62dafbb8cd39aafe63",
      "shared_idle_anchor": false
    },
    {
      "direction": "SW",
      "direction_word": "south-west",
      "frame_index": 5,
      "phase": "recover",
      "pose_png": "walk/SW/frame_005.png",
      "openpose_json": "walk/SW/frame_005.openpose.json",
      "sha256": "bf22f0ff3b68fcef6c690e7ebf8ece365746df811657d68196ec261154b9d0e8",
      "shared_idle_anchor": false
    }
  ]
}